LICENSE
README.md
setup.py
langvec/__init__.py
langvec/constants.py
langvec/langvec.py
langvec/test_langvec.py
langvec.egg-info/PKG-INFO
langvec.egg-info/SOURCES.txt
langvec.egg-info/dependency_links.txt
langvec.egg-info/requires.txt
langvec.egg-info/top_level.txt