Metadata-Version: 2.1
Name: langvec
Version: 0.0.2
Summary: Language of Vectors (LangVec) is a simple Python library designed for transforming numerical vector data into a language-like structure using a predefined set of words (lexicon).
Author: Simeon Emanuilov
Author-email: simeon.emanuilov@gmail.com
License: MIT
Keywords: langvec semantic search vectorization
Classifier: License :: OSI Approved :: MIT License
Classifier: Intended Audience :: Developers
Classifier: Intended Audience :: Education
Classifier: Intended Audience :: Science/Research
Classifier: Programming Language :: Python :: 3
Classifier: Programming Language :: Python :: 3 :: Only
Classifier: Topic :: Scientific/Engineering
Classifier: Topic :: Scientific/Engineering :: Mathematics
Classifier: Topic :: Scientific/Engineering :: Artificial Intelligence
Classifier: Topic :: Software Development
Classifier: Topic :: Software Development :: Libraries
Classifier: Topic :: Software Development :: Libraries :: Python Modules
Requires-Python: >=3.00
License-File: LICENSE
Requires-Dist: numpy
